antarctic/__init__.py
antarctic/document.py
antarctic/pandas_field.py
antarctic-0.9.5.dist-info/METADATA
antarctic-0.9.5.dist-info/WHEEL
antarctic-0.9.5.dist-info/licenses/LICENSE
antarctic-0.9.5.dist-info/RECORD
