Metadata-Version: 2.4
Name: antarctic
Version: 0.9.5
Summary: ...
Project-URL: repository, https://github.com/tschm/antarctic
Project-URL: homepage, https://tschm.github.io/antarctic/book
Author-email: Thomas Schmelzer <thomas.schmelzer@gmail.com>
License-File: LICENSE
Requires-Python: >=3.11
Requires-Dist: fastparquet>=0.8.0
Requires-Dist: mongoengine>=0.25.0
Requires-Dist: pandas>=2.0
Requires-Dist: pyarrow>=0.15.0
Provides-Extra: dev
Requires-Dist: mongomock==4.3.0; extra == 'dev'
Requires-Dist: pre-commit==4.2.0; extra == 'dev'
Requires-Dist: pytest-cov==6.2.1; extra == 'dev'
Requires-Dist: pytest==8.4.1; extra == 'dev'
Requires-Dist: python-dotenv==1.1.1; extra == 'dev'
